{
  "config": {
    "isp_electric_s": 2000.0,
    "isp_hydrolox_s": 450.0,
    "chunk_t": 200.0,
    "v_earth_orbit_km_s": 29.784691831696804,
    "v_saturn_orbit_km_s": 9.621691565667968,
    "dv_saturn_spiral_he_km_s": 6.159,
    "lga_credit_km_s": 2.0,
    "ceiling_yr": 15.0
  },
  "hohmann_baseline": {
    "a_km": 791567213.2349099,
    "r_apo_km": 1433536555.7698197,
    "v_perihelion_km_s": 40.08238898319444,
    "v_at_r_Saturn_km_s": 4.182830232211972,
    "dv_departure_km_s": 10.297697151497637,
    "dv_arrival_km_s": 5.438861333455995,
    "dv_total_helio_km_s": 15.736558484953633,
    "cruise_yr": 6.085857577229889
  },
  "transfers": [
    {
      "feasible": true,
      "r_apo_km": 1433536555.7698197,
      "r_apo_AU": 9.582600044839007,
      "a_km": 791567213.2349099,
      "eccentricity": 0.8110105267136619,
      "v_perihelion_km_s": 40.08238898319444,
      "v_total_at_r_Saturn_km_s": 4.182830232211972,
      "v_theta_at_r_Saturn_km_s": 4.182830232211972,
      "v_radial_at_r_Saturn_km_s": 0.0,
      "dv_departure_helio_km_s": 10.297697151497637,
      "dv_arrival_helio_km_s": 5.438861333455995,
      "dv_total_helio_km_s": 15.736558484953633,
      "cruise_yr": 6.085857577229889
    },
    {
      "feasible": true,
      "r_apo_km": 1570777635.0,
      "r_apo_AU": 10.5,
      "a_km": 860187752.85,
      "eccentricity": 0.8260869557787264,
      "v_perihelion_km_s": 40.248883549314144,
      "v_total_at_r_Saturn_km_s": 5.5561487666953235,
      "v_theta_at_r_Saturn_km_s": 4.200204907782245,
      "v_radial_at_r_Saturn_km_s": 3.637178556283965,
      "dv_departure_helio_km_s": 10.46419171761734,
      "dv_arrival_helio_km_s": 6.5285209222246365,
      "dv_total_helio_km_s": 16.992712639841976,
      "cruise_yr": 4.436384062780449
    },
    {
      "feasible": true,
      "r_apo_km": 1645576570.0,
      "r_apo_AU": 11.0,
      "a_km": 897587220.35,
      "eccentricity": 0.8333333326184538,
      "v_perihelion_km_s": 40.328663377295875,
      "v_total_at_r_Saturn_km_s": 6.107311352030864,
      "v_theta_at_r_Saturn_km_s": 4.208530396478605,
      "v_radial_at_r_Saturn_km_s": 4.425779462711704,
      "dv_departure_helio_km_s": 10.54397154559907,
      "dv_arrival_helio_km_s": 6.9921268363910745,
      "dv_total_helio_km_s": 17.536098381990143,
      "cruise_yr": 4.183054624003976
    },
    {
      "feasible": true,
      "r_apo_km": 1795174440.0,
      "r_apo_AU": 12.0,
      "a_km": 972386155.35,
      "eccentricity": 0.8461538454893428,
      "v_perihelion_km_s": 40.46942702884204,
      "v_total_at_r_Saturn_km_s": 6.97658126836994,
      "v_theta_at_r_Saturn_km_s": 4.223219901575987,
      "v_radial_at_r_Saturn_km_s": 5.553116229388939,
      "dv_departure_helio_km_s": 10.684735197145237,
      "dv_arrival_helio_km_s": 7.744714078977149,
      "dv_total_helio_km_s": 18.429449276122387,
      "cruise_yr": 3.8639666830052346
    },
    {
      "feasible": true,
      "r_apo_km": 2094370180.0,
      "r_apo_AU": 14.0,
      "a_km": 1121984025.35,
      "eccentricity": 0.866666666084365,
      "v_perihelion_km_s": 40.69363609747636,
      "v_total_at_r_Saturn_km_s": 8.177418968429459,
      "v_theta_at_r_Saturn_km_s": 4.246617420895828,
      "v_radial_at_r_Saturn_km_s": 6.988306051238309,
      "dv_departure_helio_km_s": 10.908944265779553,
      "dv_arrival_helio_km_s": 8.816339576466637,
      "dv_total_helio_km_s": 19.725283842246192,
      "cruise_yr": 3.517388973074825
    },
    {
      "feasible": true,
      "r_apo_km": 2543163790.0,
      "r_apo_AU": 17.0,
      "a_km": 1346380830.35,
      "eccentricity": 0.8888888883978607,
      "v_perihelion_km_s": 40.935143477531824,
      "v_total_at_r_Saturn_km_s": 9.305059574098145,
      "v_theta_at_r_Saturn_km_s": 4.2718201195429035,
      "v_radial_at_r_Saturn_km_s": 8.266540179771946,
      "dv_departure_helio_km_s": 11.15045164583502,
      "dv_arrival_helio_km_s": 9.846664970123046,
      "dv_total_helio_km_s": 20.997116615958063,
      "cruise_yr": 3.253704850496824
    },
    {
      "feasible": true,
      "r_apo_km": 2991957400.0,
      "r_apo_AU": 20.0,
      "a_km": 1570777635.35,
      "eccentricity": 0.9047619043374866,
      "v_perihelion_km_s": 41.106780052779314,
      "v_total_at_r_Saturn_km_s": 10.033221240408018,
      "v_theta_at_r_Saturn_km_s": 4.289731393648834,
      "v_radial_at_r_Saturn_km_s": 9.069935668422254,
      "dv_departure_helio_km_s": 11.32208822108251,
      "dv_arrival_helio_km_s": 10.52109938672364,
      "dv_total_helio_km_s": 21.84318760780615,
      "cruise_yr": 3.105838624296782
    },
    {
      "feasible": true,
      "r_apo_km": 3739946750.0,
      "r_apo_AU": 25.0,
      "a_km": 1944772310.35,
      "eccentricity": 0.9230769227308276,
      "v_perihelion_km_s": 41.30393600515877,
      "v_total_at_r_Saturn_km_s": 10.812644989531934,
      "v_theta_at_r_Saturn_km_s": 4.310305763066263,
      "v_radial_at_r_Saturn_km_s": 9.916378164356571,
      "dv_departure_helio_km_s": 11.519244173461963,
      "dv_arrival_helio_km_s": 11.24923886503468,
      "dv_total_helio_km_s": 22.768483038496644,
      "cruise_yr": 2.96285841555437
    },
    {
      "feasible": true,
      "r_apo_km": 4487936100.0,
      "r_apo_AU": 30.0,
      "a_km": 2318766985.35,
      "eccentricity": 0.9354838706755957,
      "v_perihelion_km_s": 41.43696029863665,
      "v_total_at_r_Saturn_km_s": 11.310165380850496,
      "v_theta_at_r_Saturn_km_s": 4.324187621171357,
      "v_radial_at_r_Saturn_km_s": 10.450896725118731,
      "dv_departure_helio_km_s": 11.652268466939844,
      "dv_arrival_helio_km_s": 11.71685923791246,
      "dv_total_helio_km_s": 23.369127704852303,
      "cruise_yr": 2.878641196475689
    },
    {
      "feasible": true,
      "r_apo_km": 5983914800.0,
      "r_apo_AU": 40.0,
      "a_km": 3066756335.35,
      "eccentricity": 0.951219511972435,
      "v_perihelion_km_s": 41.60506224846135,
      "v_total_at_r_Saturn_km_s": 11.911312557805836,
      "v_theta_at_r_Saturn_km_s": 4.341730036572679,
      "v_radial_at_r_Saturn_km_s": 11.091832451820826,
      "dv_departure_helio_km_s": 11.820370416764547,
      "dv_arrival_helio_km_s": 12.284410481907216,
      "dv_total_helio_km_s": 24.104780898671763,
      "cruise_yr": 2.7832812769288076
    },
    {
      "feasible": true,
      "r_apo_km": 8975872200.0,
      "r_apo_AU": 60.0,
      "a_km": 4562735035.35,
      "eccentricity": 0.9672131146031965,
      "v_perihelion_km_s": 41.77522681319588,
      "v_total_at_r_Saturn_km_s": 12.492707370516582,
      "v_theta_at_r_Saturn_km_s": 4.359487697826882,
      "v_radial_at_r_Saturn_km_s": 11.707373935168185,
      "dv_departure_helio_km_s": 11.990534981499074,
      "dv_arrival_helio_km_s": 12.835629863959815,
      "dv_total_helio_km_s": 24.82616484545889,
      "cruise_yr": 2.697011606694701
    }
  ],
  "closures_500kwe": [
    {
      "feasible": true,
      "reactor_kwe": 500.0,
      "cruise_yr": 6.085857577229889,
      "r_apo_AU": 9.582600044839007,
      "dv_helio_departure_km_s": 10.297697151497637,
      "dv_helio_arrival_km_s": 5.438861333455995,
      "dv_helio_total_km_s": 15.736558484953633,
      "dv_inbound_electric_km_s": 19.895558484953632,
      "m_tug_t": 63.36742509821083,
      "m_outbound_kick_prop_t": 683.3389611720502,
      "m_LEO_mission1_t": 756.706386270261,
      "m_prop_inbound_t": 167.86429822469358,
      "delivered_t": 32.135701775306416,
      "delivered_fraction": 0.16067850887653207,
      "thrust_inbound_N": 33.14077692178267,
      "mass_ratio_inbound": 2.757683946612994,
      "t_inbound_burn_yr": 3.148055337640789,
      "round_trip_yr": 16.319770492100567,
      "closes_strict_15yr": false,
      "closes_soft_16yr": false,
      "closes_double_soft_17yr": true
    },
    {
      "feasible": true,
      "reactor_kwe": 500.0,
      "cruise_yr": 4.436384062780449,
      "r_apo_AU": 10.5,
      "dv_helio_departure_km_s": 10.46419171761734,
      "dv_helio_arrival_km_s": 6.5285209222246365,
      "dv_helio_total_km_s": 16.992712639841976,
      "dv_inbound_electric_km_s": 21.151712639841975,
      "m_tug_t": 63.673774638910295,
      "m_outbound_kick_prop_t": 715.4083804291884,
      "m_LEO_mission1_t": 789.0821550680987,
      "m_prop_inbound_t": 173.99128903868282,
      "delivered_t": 26.008710961317178,
      "delivered_fraction": 0.1300435548065859,
      "thrust_inbound_N": 33.14077692178267,
      "mass_ratio_inbound": 2.940081245683104,
      "t_inbound_burn_yr": 3.26295830592912,
      "round_trip_yr": 13.135726431490017,
      "closes_strict_15yr": true,
      "closes_soft_16yr": true,
      "closes_double_soft_17yr": true
    },
    {
      "feasible": true,
      "reactor_kwe": 500.0,
      "cruise_yr": 4.183054624003976,
      "r_apo_AU": 11.0,
      "dv_helio_departure_km_s": 10.54397154559907,
      "dv_helio_arrival_km_s": 6.9921268363910745,
      "dv_helio_total_km_s": 17.536098381990143,
      "dv_inbound_electric_km_s": 21.695098381990146,
      "m_tug_t": 63.800543427159226,
      "m_outbound_kick_prop_t": 731.0592044741968,
      "m_LEO_mission1_t": 804.8597479013561,
      "m_prop_inbound_t": 176.52666480366148,
      "delivered_t": 23.473335196338525,
      "delivered_fraction": 0.11736667598169262,
      "thrust_inbound_N": 33.14077692178267,
      "mass_ratio_inbound": 3.0226749310601844,
      "t_inbound_burn_yr": 3.310505659918487,
      "round_trip_yr": 12.676614907926439,
      "closes_strict_15yr": true,
      "closes_soft_16yr": true,
      "closes_double_soft_17yr": true
    },
    {
      "feasible": true,
      "reactor_kwe": 500.0,
      "cruise_yr": 3.8639666830052346,
      "r_apo_AU": 12.0,
      "dv_helio_departure_km_s": 10.684735197145237,
      "dv_helio_arrival_km_s": 7.744714078977149,
      "dv_helio_total_km_s": 18.429449276122387,
      "dv_inbound_electric_km_s": 22.588449276122386,
      "m_tug_t": 64.00172255299084,
      "m_outbound_kick_prop_t": 759.2100696633927,
      "m_LEO_mission1_t": 833.2117922163835,
      "m_prop_inbound_t": 180.55024732029383,
      "delivered_t": 19.449752679706165,
      "delivered_fraction": 0.09724876339853082,
      "thrust_inbound_N": 33.14077692178267,
      "mass_ratio_inbound": 3.1635360262689627,
      "t_inbound_burn_yr": 3.385962207569662,
      "round_trip_yr": 12.11389557358013,
      "closes_strict_15yr": true,
      "closes_soft_16yr": true,
      "closes_double_soft_17yr": true
    },
    {
      "feasible": true,
      "reactor_kwe": 500.0,
      "cruise_yr": 3.517388973074825,
      "r_apo_AU": 14.0,
      "dv_helio_departure_km_s": 10.908944265779553,
      "dv_helio_arrival_km_s": 8.816339576466637,
      "dv_helio_total_km_s": 19.725283842246192,
      "dv_inbound_electric_km_s": 23.88428384224619,
      "m_tug_t": 64.27822572549117,
      "m_outbound_kick_prop_t": 805.6355532045862,
      "m_LEO_mission1_t": 879.9137789300775,
      "m_prop_inbound_t": 186.0803107703004,
      "delivered_t": 13.9196892296996,
      "delivered_fraction": 0.069598446148498,
      "thrust_inbound_N": 33.14077692178267,
      "mass_ratio_inbound": 3.379607483012849,
      "t_inbound_burn_yr": 3.4896706550799403,
      "round_trip_yr": 11.52444860122959,
      "closes_strict_15yr": true,
      "closes_soft_16yr": true,
      "closes_double_soft_17yr": true
    },
    {
      "feasible": true,
      "reactor_kwe": 500.0,
      "cruise_yr": 3.253704850496824,
      "r_apo_AU": 17.0,
      "dv_helio_departure_km_s": 11.15045164583502,
      "dv_helio_arrival_km_s": 9.846664970123046,
      "dv_helio_total_km_s": 20.997116615958063,
      "dv_inbound_electric_km_s": 25.156116615958066,
      "m_tug_t": 64.53292216710847,
      "m_outbound_kick_prop_t": 858.0643438377294,
      "m_LEO_mission1_t": 932.5972660048379,
      "m_prop_inbound_t": 191.17423960264645,
      "delivered_t": 8.825760397353548,
      "delivered_fraction": 0.04412880198676774,
      "thrust_inbound_N": 33.14077692178267,
      "mass_ratio_inbound": 3.6060211804861826,
      "t_inbound_burn_yr": 3.585200020286379,
      "round_trip_yr": 11.092609721280027,
      "closes_strict_15yr": true,
      "closes_soft_16yr": true,
      "closes_double_soft_17yr": true
    },
    {
      "feasible": true,
      "reactor_kwe": 500.0,
      "cruise_yr": 3.105838624296782,
      "r_apo_AU": 20.0,
      "dv_helio_departure_km_s": 11.32208822108251,
      "dv_helio_arrival_km_s": 10.52109938672364,
      "dv_helio_total_km_s": 21.84318760780615,
      "dv_inbound_electric_km_s": 26.00218760780615,
      "m_tug_t": 64.69368706213615,
      "m_outbound_kick_prop_t": 896.9814826691851,
      "m_LEO_mission1_t": 971.6751697313213,
      "m_prop_inbound_t": 194.38953750319996,
      "delivered_t": 5.610462496800039,
      "delivered_fraction": 0.028052312484000197,
      "thrust_inbound_N": 33.14077692178267,
      "mass_ratio_inbound": 3.7649802435035937,
      "t_inbound_burn_yr": 3.6454983435450514,
      "round_trip_yr": 10.857175592138615,
      "closes_strict_15yr": true,
      "closes_soft_16yr": true,
      "closes_double_soft_17yr": true
    },
    {
      "feasible": true,
      "reactor_kwe": 500.0,
      "cruise_yr": 2.96285841555437,
      "r_apo_AU": 25.0,
      "dv_helio_departure_km_s": 11.519244173461963,
      "dv_helio_arrival_km_s": 11.24923886503468,
      "dv_helio_total_km_s": 22.768483038496644,
      "dv_inbound_electric_km_s": 26.927483038496643,
      "m_tug_t": 64.8619543579152,
      "m_outbound_kick_prop_t": 943.4973042829215,
      "m_LEO_mission1_t": 1018.3592586408367,
      "m_prop_inbound_t": 197.75488341878093,
      "delivered_t": 2.245116581219065,
      "delivered_fraction": 0.011225582906095327,
      "thrust_inbound_N": 33.14077692178267,
      "mass_ratio_inbound": 3.9468569426755002,
      "t_inbound_burn_yr": 3.708610603177361,
      "round_trip_yr": 10.634327434286101,
      "closes_strict_15yr": true,
      "closes_soft_16yr": true,
      "closes_double_soft_17yr": true
    },
    {
      "feasible": true,
      "reactor_kwe": 500.0,
      "cruise_yr": 2.878641196475689,
      "r_apo_AU": 30.0,
      "dv_helio_departure_km_s": 11.652268466939844,
      "dv_helio_arrival_km_s": 11.71685923791246,
      "dv_helio_total_km_s": 23.369127704852303,
      "dv_inbound_electric_km_s": 27.528127704852306,
      "m_tug_t": 64.96711849701826,
      "m_outbound_kick_prop_t": 976.0310347561864,
      "m_LEO_mission1_t": 1050.9981532532047,
      "m_prop_inbound_t": 199.8581662008422,
      "delivered_t": 0.14183379915780847,
      "delivered_fraction": 0.0007091689957890424,
      "thrust_inbound_N": 33.14077692178267,
      "mass_ratio_inbound": 4.069596712382378,
      "t_inbound_burn_yr": 3.748054669954283,
      "round_trip_yr": 10.50533706290566,
      "closes_strict_15yr": true,
      "closes_soft_16yr": true,
      "closes_double_soft_17yr": true
    },
    {
      "feasible": false,
      "reason": "electric inbound 28.26 km/s requires 202.1 t > chunk 200.0 t",
      "cruise_yr": 2.7832812769288076,
      "dv_inbound_electric_km_s": 28.26378089867176,
      "round_trip_yr": Infinity,
      "delivered_t": -Infinity
    },
    {
      "feasible": false,
      "reason": "electric inbound 28.99 km/s requires 204.4 t > chunk 200.0 t",
      "cruise_yr": 2.697011606694701,
      "dv_inbound_electric_km_s": 28.98516484545889,
      "round_trip_yr": Infinity,
      "delivered_t": -Infinity
    }
  ],
  "closures_1000kwe": [
    {
      "feasible": false,
      "reason": "electric inbound 19.90 km/s requires 200.6 t > chunk 200.0 t",
      "cruise_yr": 6.085857577229889,
      "dv_inbound_electric_km_s": 19.895558484953632,
      "round_trip_yr": Infinity,
      "delivered_t": -Infinity
    },
    {
      "feasible": false,
      "reason": "electric inbound 21.15 km/s requires 201.2 t > chunk 200.0 t",
      "cruise_yr": 4.436384062780449,
      "dv_inbound_electric_km_s": 21.151712639841975,
      "round_trip_yr": Infinity,
      "delivered_t": -Infinity
    },
    {
      "feasible": false,
      "reason": "electric inbound 21.70 km/s requires 204.1 t > chunk 200.0 t",
      "cruise_yr": 4.183054624003976,
      "dv_inbound_electric_km_s": 21.695098381990146,
      "round_trip_yr": Infinity,
      "delivered_t": -Infinity
    },
    {
      "feasible": false,
      "reason": "electric inbound 22.59 km/s requires 208.6 t > chunk 200.0 t",
      "cruise_yr": 3.8639666830052346,
      "dv_inbound_electric_km_s": 22.588449276122386,
      "round_trip_yr": Infinity,
      "delivered_t": -Infinity
    },
    {
      "feasible": false,
      "reason": "electric inbound 23.88 km/s requires 214.7 t > chunk 200.0 t",
      "cruise_yr": 3.517388973074825,
      "dv_inbound_electric_km_s": 23.88428384224619,
      "round_trip_yr": Infinity,
      "delivered_t": -Infinity
    },
    {
      "feasible": false,
      "reason": "electric inbound 25.16 km/s requires 220.4 t > chunk 200.0 t",
      "cruise_yr": 3.253704850496824,
      "dv_inbound_electric_km_s": 25.156116615958066,
      "round_trip_yr": Infinity,
      "delivered_t": -Infinity
    },
    {
      "feasible": false,
      "reason": "electric inbound 26.00 km/s requires 224.0 t > chunk 200.0 t",
      "cruise_yr": 3.105838624296782,
      "dv_inbound_electric_km_s": 26.00218760780615,
      "round_trip_yr": Infinity,
      "delivered_t": -Infinity
    },
    {
      "feasible": false,
      "reason": "electric inbound 26.93 km/s requires 227.7 t > chunk 200.0 t",
      "cruise_yr": 2.96285841555437,
      "dv_inbound_electric_km_s": 26.927483038496643,
      "round_trip_yr": Infinity,
      "delivered_t": -Infinity
    },
    {
      "feasible": false,
      "reason": "electric inbound 27.53 km/s requires 230.0 t > chunk 200.0 t",
      "cruise_yr": 2.878641196475689,
      "dv_inbound_electric_km_s": 27.528127704852306,
      "round_trip_yr": Infinity,
      "delivered_t": -Infinity
    },
    {
      "feasible": false,
      "reason": "electric inbound 28.26 km/s requires 232.8 t > chunk 200.0 t",
      "cruise_yr": 2.7832812769288076,
      "dv_inbound_electric_km_s": 28.26378089867176,
      "round_trip_yr": Infinity,
      "delivered_t": -Infinity
    },
    {
      "feasible": false,
      "reason": "electric inbound 28.99 km/s requires 235.4 t > chunk 200.0 t",
      "cruise_yr": 2.697011606694701,
      "dv_inbound_electric_km_s": 28.98516484545889,
      "round_trip_yr": Infinity,
      "delivered_t": -Infinity
    }
  ],
  "hypothesis_grading": {
    "H-cto-a_helio_dv_at_4yr_cruise": {
      "predicted_range_km_s": [
        24.0,
        32.0
      ],
      "point_km_s": 28.0,
      "actual_helio_total_km_s_at_4yr_cruise": 18.429449276122387,
      "actual_cruise_yr": 3.8639666830052346,
      "held": false
    },
    "H-cto-b_round_trip_at_4yr_cruise": {
      "predicted_range_yr": [
        15.0,
        18.0
      ],
      "point_yr": 16.5,
      "actual_round_trip_yr": 12.11389557358013,
      "actual_delivered_t": 19.449752679706165,
      "held": false
    },
    "H-cto-c_optimal_cruise_yr": {
      "predicted_range_yr": [
        5.5,
        6.5
      ],
      "point_yr": 6.0,
      "actual_optimal_cruise_yr": 2.878641196475689,
      "held": false
    },
    "H-cto-d_round_trip_improvement": {
      "predicted_range_yr": [
        0.0,
        0.7
      ],
      "point_yr": 0.3,
      "actual_round_trip_improvement_yr": 5.8144334291949065,
      "hohmann_rt": 16.319770492100567,
      "optimal_rt": 10.50533706290566,
      "held": false
    },
    "H-cto-e_kick_prop_at_4yr": {
      "predicted_range_t": [
        200.0,
        Infinity
      ],
      "point_t": 280.0,
      "actual_kick_prop_t_at_4yr": 759.2100696633927,
      "held": true
    }
  }
}