{
 "findings": {
  "H1": {
   "worst_n1_lpd_ratio_vs_mono": 0.9,
   "held": false
  },
  "H2": {
   "best_paper": {
    "cell": {
     "launch_t": 73.0,
     "lpd": 0.36,
     "water_t": 76.9,
     "t_sortie": 2.08,
     "residence": 11.4,
     "strict": false,
     "waiver": true,
     "kappa": 100.0,
     "p_s": 60,
     "n": 5
    },
    "edge_vs_mono": 0.65,
    "at_min_power": true
   },
   "best_flown": {
    "cell": {
     "launch_t": 159.7,
     "lpd": 1.33,
     "water_t": 117.0,
     "t_sortie": 3.8,
     "residence": 12.4,
     "strict": false,
     "waiver": true,
     "kappa": 417.0,
     "p_s": 50,
     "n": 3
    },
    "edge_vs_mono": 0.45,
    "at_min_power": true
   },
   "mono_lpd": {
    "100.0": 1.02,
    "417.0": 2.41
   },
   "held": false
  },
  "H3": {
   "strict_n2_power_frontier_kwe": 193.0,
   "lpd_at_frontier": 1.88,
   "strict_cells_beating_mono": 0,
   "held": true
  },
  "H4": {
   "harvest_ratio_relay_win_cell": 2.9,
   "harvest_ratio_mono": 3.5,
   "worst_flown_harvest_ratio": 9.6,
   "mothership_ring_crossings": 0,
   "monolithic_ring_crossings": 2,
   "held": true
  }
 },
 "sweep": [
  {
   "launch_t": 49.6,
   "lpd": 1.24,
   "water_t": 66.1,
   "t_sortie": 5.37,
   "residence": 6.4,
   "strict": false,
   "waiver": true,
   "kappa": 100.0,
   "p_s": 20,
   "n": 1
  },
  {
   "launch_t": 49.6,
   "lpd": 0.62,
   "water_t": 66.1,
   "t_sortie": 5.37,
   "residence": 11.7,
   "strict": false,
   "waiver": true,
   "kappa": 100.0,
   "p_s": 20,
   "n": 2
  },
  {
   "launch_t": 49.6,
   "lpd": 0.41,
   "water_t": 66.1,
   "t_sortie": 5.37,
   "residence": 17.1,
   "strict": false,
   "waiver": false,
   "kappa": 100.0,
   "p_s": 20,
   "n": 3
  },
  {
   "launch_t": 49.6,
   "lpd": 0.31,
   "water_t": 66.1,
   "t_sortie": 5.37,
   "residence": 22.5,
   "strict": false,
   "waiver": false,
   "kappa": 100.0,
   "p_s": 20,
   "n": 4
  },
  {
   "launch_t": 49.6,
   "lpd": 0.25,
   "water_t": 66.1,
   "t_sortie": 5.37,
   "residence": 27.9,
   "strict": false,
   "waiver": false,
   "kappa": 100.0,
   "p_s": 20,
   "n": 5
  },
  {
   "launch_t": 55.5,
   "lpd": 1.39,
   "water_t": 68.8,
   "t_sortie": 3.73,
   "residence": 4.7,
   "strict": false,
   "waiver": true,
   "kappa": 100.0,
   "p_s": 30,
   "n": 1
  },
  {
   "launch_t": 55.5,
   "lpd": 0.69,
   "water_t": 68.8,
   "t_sortie": 3.73,
   "residence": 8.5,
   "strict": false,
   "waiver": true,
   "kappa": 100.0,
   "p_s": 30,
   "n": 2
  },
  {
   "launch_t": 55.5,
   "lpd": 0.46,
   "water_t": 68.8,
   "t_sortie": 3.73,
   "residence": 12.2,
   "strict": false,
   "waiver": true,
   "kappa": 100.0,
   "p_s": 30,
   "n": 3
  },
  {
   "launch_t": 55.5,
   "lpd": 0.35,
   "water_t": 68.8,
   "t_sortie": 3.73,
   "residence": 15.9,
   "strict": false,
   "waiver": false,
   "kappa": 100.0,
   "p_s": 30,
   "n": 4
  },
  {
   "launch_t": 55.5,
   "lpd": 0.28,
   "water_t": 68.8,
   "t_sortie": 3.73,
   "residence": 19.6,
   "strict": false,
   "waiver": false,
   "kappa": 100.0,
   "p_s": 30,
   "n": 5
  },
  {
   "launch_t": 61.3,
   "lpd": 1.53,
   "water_t": 71.5,
   "t_sortie": 2.91,
   "residence": 3.9,
   "strict": false,
   "waiver": true,
   "kappa": 100.0,
   "p_s": 40,
   "n": 1
  },
  {
   "launch_t": 61.3,
   "lpd": 0.77,
   "water_t": 71.5,
   "t_sortie": 2.91,
   "residence": 6.8,
   "strict": false,
   "waiver": true,
   "kappa": 100.0,
   "p_s": 40,
   "n": 2
  },
  {
   "launch_t": 61.3,
   "lpd": 0.51,
   "water_t": 71.5,
   "t_sortie": 2.91,
   "residence": 9.7,
   "strict": false,
   "waiver": true,
   "kappa": 100.0,
   "p_s": 40,
   "n": 3
  },
  {
   "launch_t": 61.3,
   "lpd": 0.38,
   "water_t": 71.5,
   "t_sortie": 2.91,
   "residence": 12.6,
   "strict": false,
   "waiver": true,
   "kappa": 100.0,
   "p_s": 40,
   "n": 4
  },
  {
   "launch_t": 61.3,
   "lpd": 0.31,
   "water_t": 71.5,
   "t_sortie": 2.91,
   "residence": 15.5,
   "strict": false,
   "waiver": false,
   "kappa": 100.0,
   "p_s": 40,
   "n": 5
  },
  {
   "launch_t": 67.2,
   "lpd": 1.68,
   "water_t": 74.2,
   "t_sortie": 2.41,
   "residence": 3.4,
   "strict": false,
   "waiver": true,
   "kappa": 100.0,
   "p_s": 50,
   "n": 1
  },
  {
   "launch_t": 67.2,
   "lpd": 0.84,
   "water_t": 74.2,
   "t_sortie": 2.41,
   "residence": 5.8,
   "strict": false,
   "waiver": true,
   "kappa": 100.0,
   "p_s": 50,
   "n": 2
  },
  {
   "launch_t": 67.2,
   "lpd": 0.56,
   "water_t": 74.2,
   "t_sortie": 2.41,
   "residence": 8.2,
   "strict": false,
   "waiver": true,
   "kappa": 100.0,
   "p_s": 50,
   "n": 3
  },
  {
   "launch_t": 67.2,
   "lpd": 0.42,
   "water_t": 74.2,
   "t_sortie": 2.41,
   "residence": 10.6,
   "strict": false,
   "waiver": true,
   "kappa": 100.0,
   "p_s": 50,
   "n": 4
  },
  {
   "launch_t": 67.2,
   "lpd": 0.34,
   "water_t": 74.2,
   "t_sortie": 2.41,
   "residence": 13.1,
   "strict": false,
   "waiver": false,
   "kappa": 100.0,
   "p_s": 50,
   "n": 5
  },
  {
   "launch_t": 73.0,
   "lpd": 1.82,
   "water_t": 76.9,
   "t_sortie": 2.08,
   "residence": 3.1,
   "strict": false,
   "waiver": true,
   "kappa": 100.0,
   "p_s": 60,
   "n": 1
  },
  {
   "launch_t": 73.0,
   "lpd": 0.91,
   "water_t": 76.9,
   "t_sortie": 2.08,
   "residence": 5.2,
   "strict": false,
   "waiver": true,
   "kappa": 100.0,
   "p_s": 60,
   "n": 2
  },
  {
   "launch_t": 73.0,
   "lpd": 0.61,
   "water_t": 76.9,
   "t_sortie": 2.08,
   "residence": 7.2,
   "strict": false,
   "waiver": true,
   "kappa": 100.0,
   "p_s": 60,
   "n": 3
  },
  {
   "launch_t": 73.0,
   "lpd": 0.46,
   "water_t": 76.9,
   "t_sortie": 2.08,
   "residence": 9.3,
   "strict": false,
   "waiver": true,
   "kappa": 100.0,
   "p_s": 60,
   "n": 4
  },
  {
   "launch_t": 73.0,
   "lpd": 0.36,
   "water_t": 76.9,
   "t_sortie": 2.08,
   "residence": 11.4,
   "strict": false,
   "waiver": true,
   "kappa": 100.0,
   "p_s": 60,
   "n": 5
  },
  {
   "launch_t": 78.8,
   "lpd": 1.97,
   "water_t": 79.6,
   "t_sortie": 1.85,
   "residence": 2.8,
   "strict": true,
   "waiver": true,
   "kappa": 100.0,
   "p_s": 70,
   "n": 1
  },
  {
   "launch_t": 78.8,
   "lpd": 0.99,
   "water_t": 79.6,
   "t_sortie": 1.85,
   "residence": 4.7,
   "strict": false,
   "waiver": true,
   "kappa": 100.0,
   "p_s": 70,
   "n": 2
  },
  {
   "launch_t": 78.8,
   "lpd": 0.66,
   "water_t": 79.6,
   "t_sortie": 1.85,
   "residence": 6.5,
   "strict": false,
   "waiver": true,
   "kappa": 100.0,
   "p_s": 70,
   "n": 3
  },
  {
   "launch_t": 78.8,
   "lpd": 0.49,
   "water_t": 79.6,
   "t_sortie": 1.85,
   "residence": 8.4,
   "strict": false,
   "waiver": true,
   "kappa": 100.0,
   "p_s": 70,
   "n": 4
  },
  {
   "launch_t": 78.8,
   "lpd": 0.39,
   "water_t": 79.6,
   "t_sortie": 1.85,
   "residence": 10.2,
   "strict": false,
   "waiver": true,
   "kappa": 100.0,
   "p_s": 70,
   "n": 5
  },
  {
   "launch_t": 84.7,
   "lpd": 2.12,
   "water_t": 82.3,
   "t_sortie": 1.67,
   "residence": 2.7,
   "strict": true,
   "waiver": true,
   "kappa": 100.0,
   "p_s": 80,
   "n": 1
  },
  {
   "launch_t": 84.7,
   "lpd": 1.06,
   "water_t": 82.3,
   "t_sortie": 1.67,
   "residence": 4.3,
   "strict": false,
   "waiver": true,
   "kappa": 100.0,
   "p_s": 80,
   "n": 2
  },
  {
   "launch_t": 84.7,
   "lpd": 0.71,
   "water_t": 82.3,
   "t_sortie": 1.67,
   "residence": 6.0,
   "strict": false,
   "waiver": true,
   "kappa": 100.0,
   "p_s": 80,
   "n": 3
  },
  {
   "launch_t": 84.7,
   "lpd": 0.53,
   "water_t": 82.3,
   "t_sortie": 1.67,
   "residence": 7.7,
   "strict": false,
   "waiver": true,
   "kappa": 100.0,
   "p_s": 80,
   "n": 4
  },
  {
   "launch_t": 84.7,
   "lpd": 0.42,
   "water_t": 82.3,
   "t_sortie": 1.67,
   "residence": 9.4,
   "strict": false,
   "waiver": true,
   "kappa": 100.0,
   "p_s": 80,
   "n": 5
  },
  {
   "launch_t": 90.5,
   "lpd": 2.26,
   "water_t": 85.0,
   "t_sortie": 1.53,
   "residence": 2.5,
   "strict": true,
   "waiver": true,
   "kappa": 100.0,
   "p_s": 90,
   "n": 1
  },
  {
   "launch_t": 90.5,
   "lpd": 1.13,
   "water_t": 85.0,
   "t_sortie": 1.53,
   "residence": 4.1,
   "strict": false,
   "waiver": true,
   "kappa": 100.0,
   "p_s": 90,
   "n": 2
  },
  {
   "launch_t": 90.5,
   "lpd": 0.75,
   "water_t": 85.0,
   "t_sortie": 1.53,
   "residence": 5.6,
   "strict": false,
   "waiver": true,
   "kappa": 100.0,
   "p_s": 90,
   "n": 3
  },
  {
   "launch_t": 90.5,
   "lpd": 0.57,
   "water_t": 85.0,
   "t_sortie": 1.53,
   "residence": 7.1,
   "strict": false,
   "waiver": true,
   "kappa": 100.0,
   "p_s": 90,
   "n": 4
  },
  {
   "launch_t": 90.5,
   "lpd": 0.45,
   "water_t": 85.0,
   "t_sortie": 1.53,
   "residence": 8.7,
   "strict": false,
   "waiver": true,
   "kappa": 100.0,
   "p_s": 90,
   "n": 5
  },
  {
   "launch_t": 96.4,
   "lpd": 2.41,
   "water_t": 87.7,
   "t_sortie": 1.43,
   "residence": 2.4,
   "strict": true,
   "waiver": true,
   "kappa": 100.0,
   "p_s": 100,
   "n": 1
  },
  {
   "launch_t": 96.4,
   "lpd": 1.2,
   "water_t": 87.7,
   "t_sortie": 1.43,
   "residence": 3.9,
   "strict": false,
   "waiver": true,
   "kappa": 100.0,
   "p_s": 100,
   "n": 2
  },
  {
   "launch_t": 96.4,
   "lpd": 0.8,
   "water_t": 87.7,
   "t_sortie": 1.43,
   "residence": 5.3,
   "strict": false,
   "waiver": true,
   "kappa": 100.0,
   "p_s": 100,
   "n": 3
  },
  {
   "launch_t": 96.4,
   "lpd": 0.6,
   "water_t": 87.7,
   "t_sortie": 1.43,
   "residence": 6.7,
   "strict": false,
   "waiver": true,
   "kappa": 100.0,
   "p_s": 100,
   "n": 4
  },
  {
   "launch_t": 96.4,
   "lpd": 0.48,
   "water_t": 87.7,
   "t_sortie": 1.43,
   "residence": 8.1,
   "strict": false,
   "waiver": true,
   "kappa": 100.0,
   "p_s": 100,
   "n": 5
  },
  {
   "launch_t": 102.2,
   "lpd": 2.56,
   "water_t": 90.4,
   "t_sortie": 1.34,
   "residence": 2.3,
   "strict": true,
   "waiver": true,
   "kappa": 100.0,
   "p_s": 110,
   "n": 1
  },
  {
   "launch_t": 102.2,
   "lpd": 1.28,
   "water_t": 90.4,
   "t_sortie": 1.34,
   "residence": 3.7,
   "strict": false,
   "waiver": true,
   "kappa": 100.0,
   "p_s": 110,
   "n": 2
  },
  {
   "launch_t": 102.2,
   "lpd": 0.85,
   "water_t": 90.4,
   "t_sortie": 1.34,
   "residence": 5.0,
   "strict": false,
   "waiver": true,
   "kappa": 100.0,
   "p_s": 110,
   "n": 3
  },
  {
   "launch_t": 102.2,
   "lpd": 0.64,
   "water_t": 90.4,
   "t_sortie": 1.34,
   "residence": 6.3,
   "strict": false,
   "waiver": true,
   "kappa": 100.0,
   "p_s": 110,
   "n": 4
  },
  {
   "launch_t": 102.2,
   "lpd": 0.51,
   "water_t": 90.4,
   "t_sortie": 1.34,
   "residence": 7.7,
   "strict": false,
   "waiver": true,
   "kappa": 100.0,
   "p_s": 110,
   "n": 5
  },
  {
   "launch_t": 108.0,
   "lpd": 2.7,
   "water_t": 93.1,
   "t_sortie": 1.26,
   "residence": 2.3,
   "strict": true,
   "waiver": true,
   "kappa": 100.0,
   "p_s": 120,
   "n": 1
  },
  {
   "launch_t": 108.0,
   "lpd": 1.35,
   "water_t": 93.1,
   "t_sortie": 1.26,
   "residence": 3.5,
   "strict": false,
   "waiver": true,
   "kappa": 100.0,
   "p_s": 120,
   "n": 2
  },
  {
   "launch_t": 108.0,
   "lpd": 0.9,
   "water_t": 93.1,
   "t_sortie": 1.26,
   "residence": 4.8,
   "strict": false,
   "waiver": true,
   "kappa": 100.0,
   "p_s": 120,
   "n": 3
  },
  {
   "launch_t": 108.0,
   "lpd": 0.68,
   "water_t": 93.1,
   "t_sortie": 1.26,
   "residence": 6.0,
   "strict": false,
   "waiver": true,
   "kappa": 100.0,
   "p_s": 120,
   "n": 4
  },
  {
   "launch_t": 108.0,
   "lpd": 0.54,
   "water_t": 93.1,
   "t_sortie": 1.26,
   "residence": 7.3,
   "strict": false,
   "waiver": true,
   "kappa": 100.0,
   "p_s": 120,
   "n": 5
  },
  {
   "launch_t": 113.9,
   "lpd": 2.85,
   "water_t": 95.8,
   "t_sortie": 1.2,
   "residence": 2.2,
   "strict": true,
   "waiver": true,
   "kappa": 100.0,
   "p_s": 130,
   "n": 1
  },
  {
   "launch_t": 113.9,
   "lpd": 1.42,
   "water_t": 95.8,
   "t_sortie": 1.2,
   "residence": 3.4,
   "strict": false,
   "waiver": true,
   "kappa": 100.0,
   "p_s": 130,
   "n": 2
  },
  {
   "launch_t": 113.9,
   "lpd": 0.95,
   "water_t": 95.8,
   "t_sortie": 1.2,
   "residence": 4.6,
   "strict": false,
   "waiver": true,
   "kappa": 100.0,
   "p_s": 130,
   "n": 3
  },
  {
   "launch_t": 113.9,
   "lpd": 0.71,
   "water_t": 95.8,
   "t_sortie": 1.2,
   "residence": 5.8,
   "strict": false,
   "waiver": true,
   "kappa": 100.0,
   "p_s": 130,
   "n": 4
  },
  {
   "launch_t": 113.9,
   "lpd": 0.57,
   "water_t": 95.8,
   "t_sortie": 1.2,
   "residence": 7.0,
   "strict": false,
   "waiver": true,
   "kappa": 100.0,
   "p_s": 130,
   "n": 5
  },
  {
   "launch_t": 119.7,
   "lpd": 2.99,
   "water_t": 98.5,
   "t_sortie": 1.14,
   "residence": 2.1,
   "strict": true,
   "waiver": true,
   "kappa": 100.0,
   "p_s": 140,
   "n": 1
  },
  {
   "launch_t": 119.7,
   "lpd": 1.5,
   "water_t": 98.5,
   "t_sortie": 1.14,
   "residence": 3.3,
   "strict": false,
   "waiver": true,
   "kappa": 100.0,
   "p_s": 140,
   "n": 2
  },
  {
   "launch_t": 119.7,
   "lpd": 1.0,
   "water_t": 98.5,
   "t_sortie": 1.14,
   "residence": 4.4,
   "strict": false,
   "waiver": true,
   "kappa": 100.0,
   "p_s": 140,
   "n": 3
  },
  {
   "launch_t": 119.7,
   "lpd": 0.75,
   "water_t": 98.5,
   "t_sortie": 1.14,
   "residence": 5.6,
   "strict": false,
   "waiver": true,
   "kappa": 100.0,
   "p_s": 140,
   "n": 4
  },
  {
   "launch_t": 119.7,
   "lpd": 0.6,
   "water_t": 98.5,
   "t_sortie": 1.14,
   "residence": 6.7,
   "strict": false,
   "waiver": true,
   "kappa": 100.0,
   "p_s": 140,
   "n": 5
  },
  {
   "launch_t": 125.6,
   "lpd": 3.14,
   "water_t": 101.2,
   "t_sortie": 1.1,
   "residence": 2.1,
   "strict": true,
   "waiver": true,
   "kappa": 100.0,
   "p_s": 150,
   "n": 1
  },
  {
   "launch_t": 125.6,
   "lpd": 1.57,
   "water_t": 101.2,
   "t_sortie": 1.1,
   "residence": 3.2,
   "strict": false,
   "waiver": true,
   "kappa": 100.0,
   "p_s": 150,
   "n": 2
  },
  {
   "launch_t": 125.6,
   "lpd": 1.05,
   "water_t": 101.2,
   "t_sortie": 1.1,
   "residence": 4.3,
   "strict": false,
   "waiver": true,
   "kappa": 100.0,
   "p_s": 150,
   "n": 3
  },
  {
   "launch_t": 125.6,
   "lpd": 0.78,
   "water_t": 101.2,
   "t_sortie": 1.1,
   "residence": 5.4,
   "strict": false,
   "waiver": true,
   "kappa": 100.0,
   "p_s": 150,
   "n": 4
  },
  {
   "launch_t": 125.6,
   "lpd": 0.63,
   "water_t": 101.2,
   "t_sortie": 1.1,
   "residence": 6.5,
   "strict": false,
   "waiver": true,
   "kappa": 100.0,
   "p_s": 150,
   "n": 5
  },
  {
   "launch_t": 131.4,
   "lpd": 3.29,
   "water_t": 103.9,
   "t_sortie": 1.06,
   "residence": 2.1,
   "strict": true,
   "waiver": true,
   "kappa": 100.0,
   "p_s": 160,
   "n": 1
  },
  {
   "launch_t": 131.4,
   "lpd": 1.64,
   "water_t": 103.9,
   "t_sortie": 1.06,
   "residence": 3.1,
   "strict": false,
   "waiver": true,
   "kappa": 100.0,
   "p_s": 160,
   "n": 2
  },
  {
   "launch_t": 131.4,
   "lpd": 1.09,
   "water_t": 103.9,
   "t_sortie": 1.06,
   "residence": 4.2,
   "strict": false,
   "waiver": true,
   "kappa": 100.0,
   "p_s": 160,
   "n": 3
  },
  {
   "launch_t": 131.4,
   "lpd": 0.82,
   "water_t": 103.9,
   "t_sortie": 1.06,
   "residence": 5.2,
   "strict": false,
   "waiver": true,
   "kappa": 100.0,
   "p_s": 160,
   "n": 4
  },
  {
   "launch_t": 131.4,
   "lpd": 0.66,
   "water_t": 103.9,
   "t_sortie": 1.06,
   "residence": 6.3,
   "strict": false,
   "waiver": true,
   "kappa": 100.0,
   "p_s": 160,
   "n": 5
  },
  {
   "launch_t": 137.2,
   "lpd": 3.43,
   "water_t": 106.6,
   "t_sortie": 1.02,
   "residence": 2.0,
   "strict": true,
   "waiver": true,
   "kappa": 100.0,
   "p_s": 170,
   "n": 1
  },
  {
   "launch_t": 137.2,
   "lpd": 1.72,
   "water_t": 106.6,
   "t_sortie": 1.02,
   "residence": 3.0,
   "strict": false,
   "waiver": true,
   "kappa": 100.0,
   "p_s": 170,
   "n": 2
  },
  {
   "launch_t": 137.2,
   "lpd": 1.14,
   "water_t": 106.6,
   "t_sortie": 1.02,
   "residence": 4.1,
   "strict": false,
   "waiver": true,
   "kappa": 100.0,
   "p_s": 170,
   "n": 3
  },
  {
   "launch_t": 137.2,
   "lpd": 0.86,
   "water_t": 106.6,
   "t_sortie": 1.02,
   "residence": 5.1,
   "strict": false,
   "waiver": true,
   "kappa": 100.0,
   "p_s": 170,
   "n": 4
  },
  {
   "launch_t": 137.2,
   "lpd": 0.69,
   "water_t": 106.6,
   "t_sortie": 1.02,
   "residence": 6.1,
   "strict": false,
   "waiver": true,
   "kappa": 100.0,
   "p_s": 170,
   "n": 5
  },
  {
   "launch_t": 143.1,
   "lpd": 3.58,
   "water_t": 109.3,
   "t_sortie": 0.99,
   "residence": 2.0,
   "strict": true,
   "waiver": true,
   "kappa": 100.0,
   "p_s": 180,
   "n": 1
  },
  {
   "launch_t": 143.1,
   "lpd": 1.79,
   "water_t": 109.3,
   "t_sortie": 0.99,
   "residence": 3.0,
   "strict": false,
   "waiver": true,
   "kappa": 100.0,
   "p_s": 180,
   "n": 2
  },
  {
   "launch_t": 143.1,
   "lpd": 1.19,
   "water_t": 109.3,
   "t_sortie": 0.99,
   "residence": 4.0,
   "strict": false,
   "waiver": true,
   "kappa": 100.0,
   "p_s": 180,
   "n": 3
  },
  {
   "launch_t": 143.1,
   "lpd": 0.89,
   "water_t": 109.3,
   "t_sortie": 0.99,
   "residence": 4.9,
   "strict": false,
   "waiver": true,
   "kappa": 100.0,
   "p_s": 180,
   "n": 4
  },
  {
   "launch_t": 143.1,
   "lpd": 0.72,
   "water_t": 109.3,
   "t_sortie": 0.99,
   "residence": 5.9,
   "strict": false,
   "waiver": true,
   "kappa": 100.0,
   "p_s": 180,
   "n": 5
  },
  {
   "launch_t": 148.9,
   "lpd": 3.72,
   "water_t": 112.0,
   "t_sortie": 0.96,
   "residence": 2.0,
   "strict": true,
   "waiver": true,
   "kappa": 100.0,
   "p_s": 190,
   "n": 1
  },
  {
   "launch_t": 148.9,
   "lpd": 1.86,
   "water_t": 112.0,
   "t_sortie": 0.96,
   "residence": 2.9,
   "strict": false,
   "waiver": true,
   "kappa": 100.0,
   "p_s": 190,
   "n": 2
  },
  {
   "launch_t": 148.9,
   "lpd": 1.24,
   "water_t": 112.0,
   "t_sortie": 0.96,
   "residence": 3.9,
   "strict": false,
   "waiver": true,
   "kappa": 100.0,
   "p_s": 190,
   "n": 3
  },
  {
   "launch_t": 148.9,
   "lpd": 0.93,
   "water_t": 112.0,
   "t_sortie": 0.96,
   "residence": 4.8,
   "strict": false,
   "waiver": true,
   "kappa": 100.0,
   "p_s": 190,
   "n": 4
  },
  {
   "launch_t": 148.9,
   "lpd": 0.74,
   "water_t": 112.0,
   "t_sortie": 0.96,
   "residence": 5.8,
   "strict": false,
   "waiver": true,
   "kappa": 100.0,
   "p_s": 190,
   "n": 5
  },
  {
   "launch_t": 154.8,
   "lpd": 3.87,
   "water_t": 114.7,
   "t_sortie": 0.93,
   "residence": 1.9,
   "strict": true,
   "waiver": true,
   "kappa": 100.0,
   "p_s": 200,
   "n": 1
  },
  {
   "launch_t": 154.8,
   "lpd": 1.93,
   "water_t": 114.7,
   "t_sortie": 0.93,
   "residence": 2.9,
   "strict": true,
   "waiver": true,
   "kappa": 100.0,
   "p_s": 200,
   "n": 2
  },
  {
   "launch_t": 154.8,
   "lpd": 1.29,
   "water_t": 114.7,
   "t_sortie": 0.93,
   "residence": 3.8,
   "strict": false,
   "waiver": true,
   "kappa": 100.0,
   "p_s": 200,
   "n": 3
  },
  {
   "launch_t": 154.8,
   "lpd": 0.97,
   "water_t": 114.7,
   "t_sortie": 0.93,
   "residence": 4.7,
   "strict": false,
   "waiver": true,
   "kappa": 100.0,
   "p_s": 200,
   "n": 4
  },
  {
   "launch_t": 154.8,
   "lpd": 0.77,
   "water_t": 114.7,
   "t_sortie": 0.93,
   "residence": 5.7,
   "strict": false,
   "waiver": true,
   "kappa": 100.0,
   "p_s": 200,
   "n": 5
  },
  {
   "launch_t": 160.6,
   "lpd": 4.01,
   "water_t": 117.4,
   "t_sortie": 0.91,
   "residence": 1.9,
   "strict": true,
   "waiver": true,
   "kappa": 100.0,
   "p_s": 210,
   "n": 1
  },
  {
   "launch_t": 160.6,
   "lpd": 2.01,
   "water_t": 117.4,
   "t_sortie": 0.91,
   "residence": 2.8,
   "strict": true,
   "waiver": true,
   "kappa": 100.0,
   "p_s": 210,
   "n": 2
  },
  {
   "launch_t": 160.6,
   "lpd": 1.34,
   "water_t": 117.4,
   "t_sortie": 0.91,
   "residence": 3.7,
   "strict": false,
   "waiver": true,
   "kappa": 100.0,
   "p_s": 210,
   "n": 3
  },
  {
   "launch_t": 160.6,
   "lpd": 1.0,
   "water_t": 117.4,
   "t_sortie": 0.91,
   "residence": 4.6,
   "strict": false,
   "waiver": true,
   "kappa": 100.0,
   "p_s": 210,
   "n": 4
  },
  {
   "launch_t": 160.6,
   "lpd": 0.8,
   "water_t": 117.4,
   "t_sortie": 0.91,
   "residence": 5.5,
   "strict": false,
   "waiver": true,
   "kappa": 100.0,
   "p_s": 210,
   "n": 5
  },
  {
   "launch_t": 166.4,
   "lpd": 4.16,
   "water_t": 120.1,
   "t_sortie": 0.89,
   "residence": 1.9,
   "strict": true,
   "waiver": true,
   "kappa": 100.0,
   "p_s": 220,
   "n": 1
  },
  {
   "launch_t": 166.4,
   "lpd": 2.08,
   "water_t": 120.1,
   "t_sortie": 0.89,
   "residence": 2.8,
   "strict": true,
   "waiver": true,
   "kappa": 100.0,
   "p_s": 220,
   "n": 2
  },
  {
   "launch_t": 166.4,
   "lpd": 1.39,
   "water_t": 120.1,
   "t_sortie": 0.89,
   "residence": 3.7,
   "strict": false,
   "waiver": true,
   "kappa": 100.0,
   "p_s": 220,
   "n": 3
  },
  {
   "launch_t": 166.4,
   "lpd": 1.04,
   "water_t": 120.1,
   "t_sortie": 0.89,
   "residence": 4.5,
   "strict": false,
   "waiver": true,
   "kappa": 100.0,
   "p_s": 220,
   "n": 4
  },
  {
   "launch_t": 166.4,
   "lpd": 0.83,
   "water_t": 120.1,
   "t_sortie": 0.89,
   "residence": 5.4,
   "strict": false,
   "waiver": true,
   "kappa": 100.0,
   "p_s": 220,
   "n": 5
  },
  {
   "launch_t": 172.3,
   "lpd": 4.31,
   "water_t": 122.8,
   "t_sortie": 0.87,
   "residence": 1.9,
   "strict": true,
   "waiver": true,
   "kappa": 100.0,
   "p_s": 230,
   "n": 1
  },
  {
   "launch_t": 172.3,
   "lpd": 2.15,
   "water_t": 122.8,
   "t_sortie": 0.87,
   "residence": 2.7,
   "strict": true,
   "waiver": true,
   "kappa": 100.0,
   "p_s": 230,
   "n": 2
  },
  {
   "launch_t": 172.3,
   "lpd": 1.44,
   "water_t": 122.8,
   "t_sortie": 0.87,
   "residence": 3.6,
   "strict": false,
   "waiver": true,
   "kappa": 100.0,
   "p_s": 230,
   "n": 3
  },
  {
   "launch_t": 172.3,
   "lpd": 1.08,
   "water_t": 122.8,
   "t_sortie": 0.87,
   "residence": 4.5,
   "strict": false,
   "waiver": true,
   "kappa": 100.0,
   "p_s": 230,
   "n": 4
  },
  {
   "launch_t": 172.3,
   "lpd": 0.86,
   "water_t": 122.8,
   "t_sortie": 0.87,
   "residence": 5.3,
   "strict": false,
   "waiver": true,
   "kappa": 100.0,
   "p_s": 230,
   "n": 5
  },
  {
   "launch_t": 178.1,
   "lpd": 4.45,
   "water_t": 125.5,
   "t_sortie": 0.85,
   "residence": 1.8,
   "strict": true,
   "waiver": true,
   "kappa": 100.0,
   "p_s": 240,
   "n": 1
  },
  {
   "launch_t": 178.1,
   "lpd": 2.23,
   "water_t": 125.5,
   "t_sortie": 0.85,
   "residence": 2.7,
   "strict": true,
   "waiver": true,
   "kappa": 100.0,
   "p_s": 240,
   "n": 2
  },
  {
   "launch_t": 178.1,
   "lpd": 1.48,
   "water_t": 125.5,
   "t_sortie": 0.85,
   "residence": 3.5,
   "strict": false,
   "waiver": true,
   "kappa": 100.0,
   "p_s": 240,
   "n": 3
  },
  {
   "launch_t": 178.1,
   "lpd": 1.11,
   "water_t": 125.5,
   "t_sortie": 0.85,
   "residence": 4.4,
   "strict": false,
   "waiver": true,
   "kappa": 100.0,
   "p_s": 240,
   "n": 4
  },
  {
   "launch_t": 178.1,
   "lpd": 0.89,
   "water_t": 125.5,
   "t_sortie": 0.85,
   "residence": 5.2,
   "strict": false,
   "waiver": true,
   "kappa": 100.0,
   "p_s": 240,
   "n": 5
  },
  {
   "launch_t": 184.0,
   "lpd": 4.6,
   "water_t": 128.2,
   "t_sortie": 0.83,
   "residence": 1.8,
   "strict": true,
   "waiver": true,
   "kappa": 100.0,
   "p_s": 250,
   "n": 1
  },
  {
   "launch_t": 184.0,
   "lpd": 2.3,
   "water_t": 128.2,
   "t_sortie": 0.83,
   "residence": 2.7,
   "strict": true,
   "waiver": true,
   "kappa": 100.0,
   "p_s": 250,
   "n": 2
  },
  {
   "launch_t": 184.0,
   "lpd": 1.53,
   "water_t": 128.2,
   "t_sortie": 0.83,
   "residence": 3.5,
   "strict": false,
   "waiver": true,
   "kappa": 100.0,
   "p_s": 250,
   "n": 3
  },
  {
   "launch_t": 184.0,
   "lpd": 1.15,
   "water_t": 128.2,
   "t_sortie": 0.83,
   "residence": 4.3,
   "strict": false,
   "waiver": true,
   "kappa": 100.0,
   "p_s": 250,
   "n": 4
  },
  {
   "launch_t": 184.0,
   "lpd": 0.92,
   "water_t": 128.2,
   "t_sortie": 0.83,
   "residence": 5.2,
   "strict": false,
   "waiver": true,
   "kappa": 100.0,
   "p_s": 250,
   "n": 5
  },
  {
   "launch_t": 86.7,
   "lpd": 2.17,
   "water_t": 83.2,
   "t_sortie": 6.76,
   "residence": 7.8,
   "strict": false,
   "waiver": true,
   "kappa": 417.0,
   "p_s": 20,
   "n": 1
  },
  {
   "launch_t": 86.7,
   "lpd": 1.08,
   "water_t": 83.2,
   "t_sortie": 6.76,
   "residence": 14.5,
   "strict": false,
   "waiver": false,
   "kappa": 417.0,
   "p_s": 20,
   "n": 2
  },
  {
   "launch_t": 86.7,
   "lpd": 0.72,
   "water_t": 83.2,
   "t_sortie": 6.76,
   "residence": 21.3,
   "strict": false,
   "waiver": false,
   "kappa": 417.0,
   "p_s": 20,
   "n": 3
  },
  {
   "launch_t": 86.7,
   "lpd": 0.54,
   "water_t": 83.2,
   "t_sortie": 6.76,
   "residence": 28.0,
   "strict": false,
   "waiver": false,
   "kappa": 417.0,
   "p_s": 20,
   "n": 4
  },
  {
   "launch_t": 86.7,
   "lpd": 0.43,
   "water_t": 83.2,
   "t_sortie": 6.76,
   "residence": 34.8,
   "strict": false,
   "waiver": false,
   "kappa": 417.0,
   "p_s": 20,
   "n": 5
  },
  {
   "launch_t": 111.0,
   "lpd": 2.78,
   "water_t": 94.5,
   "t_sortie": 5.12,
   "residence": 6.1,
   "strict": false,
   "waiver": true,
   "kappa": 417.0,
   "p_s": 30,
   "n": 1
  },
  {
   "launch_t": 111.0,
   "lpd": 1.39,
   "water_t": 94.5,
   "t_sortie": 5.12,
   "residence": 11.2,
   "strict": false,
   "waiver": true,
   "kappa": 417.0,
   "p_s": 30,
   "n": 2
  },
  {
   "launch_t": 111.0,
   "lpd": 0.93,
   "water_t": 94.5,
   "t_sortie": 5.12,
   "residence": 16.4,
   "strict": false,
   "waiver": false,
   "kappa": 417.0,
   "p_s": 30,
   "n": 3
  },
  {
   "launch_t": 111.0,
   "lpd": 0.69,
   "water_t": 94.5,
   "t_sortie": 5.12,
   "residence": 21.5,
   "strict": false,
   "waiver": false,
   "kappa": 417.0,
   "p_s": 30,
   "n": 4
  },
  {
   "launch_t": 111.0,
   "lpd": 0.56,
   "water_t": 94.5,
   "t_sortie": 5.12,
   "residence": 26.6,
   "strict": false,
   "waiver": false,
   "kappa": 417.0,
   "p_s": 30,
   "n": 5
  },
  {
   "launch_t": 135.4,
   "lpd": 3.38,
   "water_t": 105.7,
   "t_sortie": 4.3,
   "residence": 5.3,
   "strict": false,
   "waiver": true,
   "kappa": 417.0,
   "p_s": 40,
   "n": 1
  },
  {
   "launch_t": 135.4,
   "lpd": 1.69,
   "water_t": 105.7,
   "t_sortie": 4.3,
   "residence": 9.6,
   "strict": false,
   "waiver": true,
   "kappa": 417.0,
   "p_s": 40,
   "n": 2
  },
  {
   "launch_t": 135.4,
   "lpd": 1.13,
   "water_t": 105.7,
   "t_sortie": 4.3,
   "residence": 13.9,
   "strict": false,
   "waiver": false,
   "kappa": 417.0,
   "p_s": 40,
   "n": 3
  },
  {
   "launch_t": 135.4,
   "lpd": 0.85,
   "water_t": 105.7,
   "t_sortie": 4.3,
   "residence": 18.2,
   "strict": false,
   "waiver": false,
   "kappa": 417.0,
   "p_s": 40,
   "n": 4
  },
  {
   "launch_t": 135.4,
   "lpd": 0.68,
   "water_t": 105.7,
   "t_sortie": 4.3,
   "residence": 22.5,
   "strict": false,
   "waiver": false,
   "kappa": 417.0,
   "p_s": 40,
   "n": 5
  },
  {
   "launch_t": 159.7,
   "lpd": 3.99,
   "water_t": 117.0,
   "t_sortie": 3.8,
   "residence": 4.8,
   "strict": false,
   "waiver": true,
   "kappa": 417.0,
   "p_s": 50,
   "n": 1
  },
  {
   "launch_t": 159.7,
   "lpd": 2.0,
   "water_t": 117.0,
   "t_sortie": 3.8,
   "residence": 8.6,
   "strict": false,
   "waiver": true,
   "kappa": 417.0,
   "p_s": 50,
   "n": 2
  },
  {
   "launch_t": 159.7,
   "lpd": 1.33,
   "water_t": 117.0,
   "t_sortie": 3.8,
   "residence": 12.4,
   "strict": false,
   "waiver": true,
   "kappa": 417.0,
   "p_s": 50,
   "n": 3
  },
  {
   "launch_t": 159.7,
   "lpd": 1.0,
   "water_t": 117.0,
   "t_sortie": 3.8,
   "residence": 16.2,
   "strict": false,
   "waiver": false,
   "kappa": 417.0,
   "p_s": 50,
   "n": 4
  },
  {
   "launch_t": 159.7,
   "lpd": 0.8,
   "water_t": 117.0,
   "t_sortie": 3.8,
   "residence": 20.0,
   "strict": false,
   "waiver": false,
   "kappa": 417.0,
   "p_s": 50,
   "n": 5
  },
  {
   "launch_t": 184.1,
   "lpd": 4.6,
   "water_t": 128.2,
   "t_sortie": 3.47,
   "residence": 4.5,
   "strict": false,
   "waiver": true,
   "kappa": 417.0,
   "p_s": 60,
   "n": 1
  },
  {
   "launch_t": 184.1,
   "lpd": 2.3,
   "water_t": 128.2,
   "t_sortie": 3.47,
   "residence": 7.9,
   "strict": false,
   "waiver": true,
   "kappa": 417.0,
   "p_s": 60,
   "n": 2
  },
  {
   "launch_t": 184.1,
   "lpd": 1.53,
   "water_t": 128.2,
   "t_sortie": 3.47,
   "residence": 11.4,
   "strict": false,
   "waiver": true,
   "kappa": 417.0,
   "p_s": 60,
   "n": 3
  },
  {
   "launch_t": 184.1,
   "lpd": 1.15,
   "water_t": 128.2,
   "t_sortie": 3.47,
   "residence": 14.9,
   "strict": false,
   "waiver": false,
   "kappa": 417.0,
   "p_s": 60,
   "n": 4
  },
  {
   "launch_t": 184.1,
   "lpd": 0.92,
   "water_t": 128.2,
   "t_sortie": 3.47,
   "residence": 18.4,
   "strict": false,
   "waiver": false,
   "kappa": 417.0,
   "p_s": 60,
   "n": 5
  },
  {
   "launch_t": 208.4,
   "lpd": 5.21,
   "water_t": 139.5,
   "t_sortie": 3.24,
   "residence": 4.2,
   "strict": false,
   "waiver": true,
   "kappa": 417.0,
   "p_s": 70,
   "n": 1
  },
  {
   "launch_t": 208.4,
   "lpd": 2.61,
   "water_t": 139.5,
   "t_sortie": 3.24,
   "residence": 7.5,
   "strict": false,
   "waiver": true,
   "kappa": 417.0,
   "p_s": 70,
   "n": 2
  },
  {
   "launch_t": 208.4,
   "lpd": 1.74,
   "water_t": 139.5,
   "t_sortie": 3.24,
   "residence": 10.7,
   "strict": false,
   "waiver": true,
   "kappa": 417.0,
   "p_s": 70,
   "n": 3
  },
  {
   "launch_t": 208.4,
   "lpd": 1.3,
   "water_t": 139.5,
   "t_sortie": 3.24,
   "residence": 14.0,
   "strict": false,
   "waiver": false,
   "kappa": 417.0,
   "p_s": 70,
   "n": 4
  },
  {
   "launch_t": 208.4,
   "lpd": 1.04,
   "water_t": 139.5,
   "t_sortie": 3.24,
   "residence": 17.2,
   "strict": false,
   "waiver": false,
   "kappa": 417.0,
   "p_s": 70,
   "n": 5
  },
  {
   "launch_t": 232.8,
   "lpd": 5.82,
   "water_t": 150.7,
   "t_sortie": 3.06,
   "residence": 4.1,
   "strict": false,
   "waiver": true,
   "kappa": 417.0,
   "p_s": 80,
   "n": 1
  },
  {
   "launch_t": 232.8,
   "lpd": 2.91,
   "water_t": 150.7,
   "t_sortie": 3.06,
   "residence": 7.1,
   "strict": false,
   "waiver": true,
   "kappa": 417.0,
   "p_s": 80,
   "n": 2
  },
  {
   "launch_t": 232.8,
   "lpd": 1.94,
   "water_t": 150.7,
   "t_sortie": 3.06,
   "residence": 10.2,
   "strict": false,
   "waiver": true,
   "kappa": 417.0,
   "p_s": 80,
   "n": 3
  },
  {
   "launch_t": 232.8,
   "lpd": 1.45,
   "water_t": 150.7,
   "t_sortie": 3.06,
   "residence": 13.2,
   "strict": false,
   "waiver": false,
   "kappa": 417.0,
   "p_s": 80,
   "n": 4
  },
  {
   "launch_t": 232.8,
   "lpd": 1.16,
   "water_t": 150.7,
   "t_sortie": 3.06,
   "residence": 16.3,
   "strict": false,
   "waiver": false,
   "kappa": 417.0,
   "p_s": 80,
   "n": 5
  },
  {
   "launch_t": 257.1,
   "lpd": 6.43,
   "water_t": 162.0,
   "t_sortie": 2.92,
   "residence": 3.9,
   "strict": false,
   "waiver": true,
   "kappa": 417.0,
   "p_s": 90,
   "n": 1
  },
  {
   "launch_t": 257.1,
   "lpd": 3.21,
   "water_t": 162.0,
   "t_sortie": 2.92,
   "residence": 6.8,
   "strict": false,
   "waiver": true,
   "kappa": 417.0,
   "p_s": 90,
   "n": 2
  },
  {
   "launch_t": 257.1,
   "lpd": 2.14,
   "water_t": 162.0,
   "t_sortie": 2.92,
   "residence": 9.8,
   "strict": false,
   "waiver": true,
   "kappa": 417.0,
   "p_s": 90,
   "n": 3
  },
  {
   "launch_t": 257.1,
   "lpd": 1.61,
   "water_t": 162.0,
   "t_sortie": 2.92,
   "residence": 12.7,
   "strict": false,
   "waiver": true,
   "kappa": 417.0,
   "p_s": 90,
   "n": 4
  },
  {
   "launch_t": 257.1,
   "lpd": 1.29,
   "water_t": 162.0,
   "t_sortie": 2.92,
   "residence": 15.6,
   "strict": false,
   "waiver": false,
   "kappa": 417.0,
   "p_s": 90,
   "n": 5
  },
  {
   "launch_t": 281.5,
   "lpd": 7.04,
   "water_t": 173.2,
   "t_sortie": 2.82,
   "residence": 3.8,
   "strict": false,
   "waiver": true,
   "kappa": 417.0,
   "p_s": 100,
   "n": 1
  },
  {
   "launch_t": 281.5,
   "lpd": 3.52,
   "water_t": 173.2,
   "t_sortie": 2.82,
   "residence": 6.6,
   "strict": false,
   "waiver": true,
   "kappa": 417.0,
   "p_s": 100,
   "n": 2
  },
  {
   "launch_t": 281.5,
   "lpd": 2.35,
   "water_t": 173.2,
   "t_sortie": 2.82,
   "residence": 9.4,
   "strict": false,
   "waiver": true,
   "kappa": 417.0,
   "p_s": 100,
   "n": 3
  },
  {
   "launch_t": 281.5,
   "lpd": 1.76,
   "water_t": 173.2,
   "t_sortie": 2.82,
   "residence": 12.3,
   "strict": false,
   "waiver": true,
   "kappa": 417.0,
   "p_s": 100,
   "n": 4
  },
  {
   "launch_t": 281.5,
   "lpd": 1.41,
   "water_t": 173.2,
   "t_sortie": 2.82,
   "residence": 15.1,
   "strict": false,
   "waiver": false,
   "kappa": 417.0,
   "p_s": 100,
   "n": 5
  },
  {
   "launch_t": 305.8,
   "lpd": 7.65,
   "water_t": 184.5,
   "t_sortie": 2.73,
   "residence": 3.7,
   "strict": false,
   "waiver": true,
   "kappa": 417.0,
   "p_s": 110,
   "n": 1
  },
  {
   "launch_t": 305.8,
   "lpd": 3.82,
   "water_t": 184.5,
   "t_sortie": 2.73,
   "residence": 6.5,
   "strict": false,
   "waiver": true,
   "kappa": 417.0,
   "p_s": 110,
   "n": 2
  },
  {
   "launch_t": 305.8,
   "lpd": 2.55,
   "water_t": 184.5,
   "t_sortie": 2.73,
   "residence": 9.2,
   "strict": false,
   "waiver": true,
   "kappa": 417.0,
   "p_s": 110,
   "n": 3
  },
  {
   "launch_t": 305.8,
   "lpd": 1.91,
   "water_t": 184.5,
   "t_sortie": 2.73,
   "residence": 11.9,
   "strict": false,
   "waiver": true,
   "kappa": 417.0,
   "p_s": 110,
   "n": 4
  },
  {
   "launch_t": 305.8,
   "lpd": 1.53,
   "water_t": 184.5,
   "t_sortie": 2.73,
   "residence": 14.6,
   "strict": false,
   "waiver": false,
   "kappa": 417.0,
   "p_s": 110,
   "n": 5
  },
  {
   "launch_t": 330.2,
   "lpd": 8.25,
   "water_t": 195.7,
   "t_sortie": 2.65,
   "residence": 3.7,
   "strict": false,
   "waiver": true,
   "kappa": 417.0,
   "p_s": 120,
   "n": 1
  },
  {
   "launch_t": 330.2,
   "lpd": 4.13,
   "water_t": 195.7,
   "t_sortie": 2.65,
   "residence": 6.3,
   "strict": false,
   "waiver": true,
   "kappa": 417.0,
   "p_s": 120,
   "n": 2
  },
  {
   "launch_t": 330.2,
   "lpd": 2.75,
   "water_t": 195.7,
   "t_sortie": 2.65,
   "residence": 9.0,
   "strict": false,
   "waiver": true,
   "kappa": 417.0,
   "p_s": 120,
   "n": 3
  },
  {
   "launch_t": 330.2,
   "lpd": 2.06,
   "water_t": 195.7,
   "t_sortie": 2.65,
   "residence": 11.6,
   "strict": false,
   "waiver": true,
   "kappa": 417.0,
   "p_s": 120,
   "n": 4
  },
  {
   "launch_t": 330.2,
   "lpd": 1.65,
   "water_t": 195.7,
   "t_sortie": 2.65,
   "residence": 14.3,
   "strict": false,
   "waiver": false,
   "kappa": 417.0,
   "p_s": 120,
   "n": 5
  },
  {
   "launch_t": 354.5,
   "lpd": 8.86,
   "water_t": 207.0,
   "t_sortie": 2.59,
   "residence": 3.6,
   "strict": false,
   "waiver": true,
   "kappa": 417.0,
   "p_s": 130,
   "n": 1
  },
  {
   "launch_t": 354.5,
   "lpd": 4.43,
   "water_t": 207.0,
   "t_sortie": 2.59,
   "residence": 6.2,
   "strict": false,
   "waiver": true,
   "kappa": 417.0,
   "p_s": 130,
   "n": 2
  },
  {
   "launch_t": 354.5,
   "lpd": 2.95,
   "water_t": 207.0,
   "t_sortie": 2.59,
   "residence": 8.8,
   "strict": false,
   "waiver": true,
   "kappa": 417.0,
   "p_s": 130,
   "n": 3
  },
  {
   "launch_t": 354.5,
   "lpd": 2.22,
   "water_t": 207.0,
   "t_sortie": 2.59,
   "residence": 11.3,
   "strict": false,
   "waiver": true,
   "kappa": 417.0,
   "p_s": 130,
   "n": 4
  },
  {
   "launch_t": 354.5,
   "lpd": 1.77,
   "water_t": 207.0,
   "t_sortie": 2.59,
   "residence": 13.9,
   "strict": false,
   "waiver": false,
   "kappa": 417.0,
   "p_s": 130,
   "n": 5
  },
  {
   "launch_t": 378.9,
   "lpd": 9.47,
   "water_t": 218.2,
   "t_sortie": 2.53,
   "residence": 3.5,
   "strict": false,
   "waiver": true,
   "kappa": 417.0,
   "p_s": 140,
   "n": 1
  },
  {
   "launch_t": 378.9,
   "lpd": 4.74,
   "water_t": 218.2,
   "t_sortie": 2.53,
   "residence": 6.1,
   "strict": false,
   "waiver": true,
   "kappa": 417.0,
   "p_s": 140,
   "n": 2
  },
  {
   "launch_t": 378.9,
   "lpd": 3.16,
   "water_t": 218.2,
   "t_sortie": 2.53,
   "residence": 8.6,
   "strict": false,
   "waiver": true,
   "kappa": 417.0,
   "p_s": 140,
   "n": 3
  },
  {
   "launch_t": 378.9,
   "lpd": 2.37,
   "water_t": 218.2,
   "t_sortie": 2.53,
   "residence": 11.1,
   "strict": false,
   "waiver": true,
   "kappa": 417.0,
   "p_s": 140,
   "n": 4
  },
  {
   "launch_t": 378.9,
   "lpd": 1.89,
   "water_t": 218.2,
   "t_sortie": 2.53,
   "residence": 13.7,
   "strict": false,
   "waiver": false,
   "kappa": 417.0,
   "p_s": 140,
   "n": 5
  },
  {
   "launch_t": 403.3,
   "lpd": 10.08,
   "water_t": 229.5,
   "t_sortie": 2.49,
   "residence": 3.5,
   "strict": false,
   "waiver": true,
   "kappa": 417.0,
   "p_s": 150,
   "n": 1
  },
  {
   "launch_t": 403.3,
   "lpd": 5.04,
   "water_t": 229.5,
   "t_sortie": 2.49,
   "residence": 6.0,
   "strict": false,
   "waiver": true,
   "kappa": 417.0,
   "p_s": 150,
   "n": 2
  },
  {
   "launch_t": 403.3,
   "lpd": 3.36,
   "water_t": 229.5,
   "t_sortie": 2.49,
   "residence": 8.5,
   "strict": false,
   "waiver": true,
   "kappa": 417.0,
   "p_s": 150,
   "n": 3
  },
  {
   "launch_t": 403.3,
   "lpd": 2.52,
   "water_t": 229.5,
   "t_sortie": 2.49,
   "residence": 10.9,
   "strict": false,
   "waiver": true,
   "kappa": 417.0,
   "p_s": 150,
   "n": 4
  },
  {
   "launch_t": 403.3,
   "lpd": 2.02,
   "water_t": 229.5,
   "t_sortie": 2.49,
   "residence": 13.4,
   "strict": false,
   "waiver": false,
   "kappa": 417.0,
   "p_s": 150,
   "n": 5
  },
  {
   "launch_t": 427.6,
   "lpd": 10.69,
   "water_t": 240.7,
   "t_sortie": 2.45,
   "residence": 3.4,
   "strict": false,
   "waiver": true,
   "kappa": 417.0,
   "p_s": 160,
   "n": 1
  },
  {
   "launch_t": 427.6,
   "lpd": 5.35,
   "water_t": 240.7,
   "t_sortie": 2.45,
   "residence": 5.9,
   "strict": false,
   "waiver": true,
   "kappa": 417.0,
   "p_s": 160,
   "n": 2
  },
  {
   "launch_t": 427.6,
   "lpd": 3.56,
   "water_t": 240.7,
   "t_sortie": 2.45,
   "residence": 8.3,
   "strict": false,
   "waiver": true,
   "kappa": 417.0,
   "p_s": 160,
   "n": 3
  },
  {
   "launch_t": 427.6,
   "lpd": 2.67,
   "water_t": 240.7,
   "t_sortie": 2.45,
   "residence": 10.8,
   "strict": false,
   "waiver": true,
   "kappa": 417.0,
   "p_s": 160,
   "n": 4
  },
  {
   "launch_t": 427.6,
   "lpd": 2.14,
   "water_t": 240.7,
   "t_sortie": 2.45,
   "residence": 13.2,
   "strict": false,
   "waiver": false,
   "kappa": 417.0,
   "p_s": 160,
   "n": 5
  },
  {
   "launch_t": 452.0,
   "lpd": 11.3,
   "water_t": 252.0,
   "t_sortie": 2.41,
   "residence": 3.4,
   "strict": false,
   "waiver": true,
   "kappa": 417.0,
   "p_s": 170,
   "n": 1
  },
  {
   "launch_t": 452.0,
   "lpd": 5.65,
   "water_t": 252.0,
   "t_sortie": 2.41,
   "residence": 5.8,
   "strict": false,
   "waiver": true,
   "kappa": 417.0,
   "p_s": 170,
   "n": 2
  },
  {
   "launch_t": 452.0,
   "lpd": 3.77,
   "water_t": 252.0,
   "t_sortie": 2.41,
   "residence": 8.2,
   "strict": false,
   "waiver": true,
   "kappa": 417.0,
   "p_s": 170,
   "n": 3
  },
  {
   "launch_t": 452.0,
   "lpd": 2.82,
   "water_t": 252.0,
   "t_sortie": 2.41,
   "residence": 10.6,
   "strict": false,
   "waiver": true,
   "kappa": 417.0,
   "p_s": 170,
   "n": 4
  },
  {
   "launch_t": 452.0,
   "lpd": 2.26,
   "water_t": 252.0,
   "t_sortie": 2.41,
   "residence": 13.0,
   "strict": false,
   "waiver": false,
   "kappa": 417.0,
   "p_s": 170,
   "n": 5
  },
  {
   "launch_t": 476.3,
   "lpd": 11.91,
   "water_t": 263.2,
   "t_sortie": 2.38,
   "residence": 3.4,
   "strict": false,
   "waiver": true,
   "kappa": 417.0,
   "p_s": 180,
   "n": 1
  },
  {
   "launch_t": 476.3,
   "lpd": 5.95,
   "water_t": 263.2,
   "t_sortie": 2.38,
   "residence": 5.8,
   "strict": false,
   "waiver": true,
   "kappa": 417.0,
   "p_s": 180,
   "n": 2
  },
  {
   "launch_t": 476.3,
   "lpd": 3.97,
   "water_t": 263.2,
   "t_sortie": 2.38,
   "residence": 8.1,
   "strict": false,
   "waiver": true,
   "kappa": 417.0,
   "p_s": 180,
   "n": 3
  },
  {
   "launch_t": 476.3,
   "lpd": 2.98,
   "water_t": 263.2,
   "t_sortie": 2.38,
   "residence": 10.5,
   "strict": false,
   "waiver": true,
   "kappa": 417.0,
   "p_s": 180,
   "n": 4
  },
  {
   "launch_t": 476.3,
   "lpd": 2.38,
   "water_t": 263.2,
   "t_sortie": 2.38,
   "residence": 12.9,
   "strict": false,
   "waiver": true,
   "kappa": 417.0,
   "p_s": 180,
   "n": 5
  },
  {
   "launch_t": 500.7,
   "lpd": 12.52,
   "water_t": 274.5,
   "t_sortie": 2.35,
   "residence": 3.3,
   "strict": false,
   "waiver": true,
   "kappa": 417.0,
   "p_s": 190,
   "n": 1
  },
  {
   "launch_t": 500.7,
   "lpd": 6.26,
   "water_t": 274.5,
   "t_sortie": 2.35,
   "residence": 5.7,
   "strict": false,
   "waiver": true,
   "kappa": 417.0,
   "p_s": 190,
   "n": 2
  },
  {
   "launch_t": 500.7,
   "lpd": 4.17,
   "water_t": 274.5,
   "t_sortie": 2.35,
   "residence": 8.0,
   "strict": false,
   "waiver": true,
   "kappa": 417.0,
   "p_s": 190,
   "n": 3
  },
  {
   "launch_t": 500.7,
   "lpd": 3.13,
   "water_t": 274.5,
   "t_sortie": 2.35,
   "residence": 10.4,
   "strict": false,
   "waiver": true,
   "kappa": 417.0,
   "p_s": 190,
   "n": 4
  },
  {
   "launch_t": 500.7,
   "lpd": 2.5,
   "water_t": 274.5,
   "t_sortie": 2.35,
   "residence": 12.7,
   "strict": false,
   "waiver": true,
   "kappa": 417.0,
   "p_s": 190,
   "n": 5
  },
  {
   "launch_t": 525.0,
   "lpd": 13.13,
   "water_t": 285.7,
   "t_sortie": 2.32,
   "residence": 3.3,
   "strict": false,
   "waiver": true,
   "kappa": 417.0,
   "p_s": 200,
   "n": 1
  },
  {
   "launch_t": 525.0,
   "lpd": 6.56,
   "water_t": 285.7,
   "t_sortie": 2.32,
   "residence": 5.6,
   "strict": false,
   "waiver": true,
   "kappa": 417.0,
   "p_s": 200,
   "n": 2
  },
  {
   "launch_t": 525.0,
   "lpd": 4.38,
   "water_t": 285.7,
   "t_sortie": 2.32,
   "residence": 8.0,
   "strict": false,
   "waiver": true,
   "kappa": 417.0,
   "p_s": 200,
   "n": 3
  },
  {
   "launch_t": 525.0,
   "lpd": 3.28,
   "water_t": 285.7,
   "t_sortie": 2.32,
   "residence": 10.3,
   "strict": false,
   "waiver": true,
   "kappa": 417.0,
   "p_s": 200,
   "n": 4
  },
  {
   "launch_t": 525.0,
   "lpd": 2.63,
   "water_t": 285.7,
   "t_sortie": 2.32,
   "residence": 12.6,
   "strict": false,
   "waiver": true,
   "kappa": 417.0,
   "p_s": 200,
   "n": 5
  },
  {
   "launch_t": 549.4,
   "lpd": 13.73,
   "water_t": 297.0,
   "t_sortie": 2.3,
   "residence": 3.3,
   "strict": false,
   "waiver": true,
   "kappa": 417.0,
   "p_s": 210,
   "n": 1
  },
  {
   "launch_t": 549.4,
   "lpd": 6.87,
   "water_t": 297.0,
   "t_sortie": 2.3,
   "residence": 5.6,
   "strict": false,
   "waiver": true,
   "kappa": 417.0,
   "p_s": 210,
   "n": 2
  },
  {
   "launch_t": 549.4,
   "lpd": 4.58,
   "water_t": 297.0,
   "t_sortie": 2.3,
   "residence": 7.9,
   "strict": false,
   "waiver": true,
   "kappa": 417.0,
   "p_s": 210,
   "n": 3
  },
  {
   "launch_t": 549.4,
   "lpd": 3.43,
   "water_t": 297.0,
   "t_sortie": 2.3,
   "residence": 10.2,
   "strict": false,
   "waiver": true,
   "kappa": 417.0,
   "p_s": 210,
   "n": 4
  },
  {
   "launch_t": 549.4,
   "lpd": 2.75,
   "water_t": 297.0,
   "t_sortie": 2.3,
   "residence": 12.5,
   "strict": false,
   "waiver": true,
   "kappa": 417.0,
   "p_s": 210,
   "n": 5
  },
  {
   "launch_t": 573.7,
   "lpd": 14.34,
   "water_t": 308.2,
   "t_sortie": 2.28,
   "residence": 3.3,
   "strict": false,
   "waiver": true,
   "kappa": 417.0,
   "p_s": 220,
   "n": 1
  },
  {
   "launch_t": 573.7,
   "lpd": 7.17,
   "water_t": 308.2,
   "t_sortie": 2.28,
   "residence": 5.6,
   "strict": false,
   "waiver": true,
   "kappa": 417.0,
   "p_s": 220,
   "n": 2
  },
  {
   "launch_t": 573.7,
   "lpd": 4.78,
   "water_t": 308.2,
   "t_sortie": 2.28,
   "residence": 7.8,
   "strict": false,
   "waiver": true,
   "kappa": 417.0,
   "p_s": 220,
   "n": 3
  },
  {
   "launch_t": 573.7,
   "lpd": 3.59,
   "water_t": 308.2,
   "t_sortie": 2.28,
   "residence": 10.1,
   "strict": false,
   "waiver": true,
   "kappa": 417.0,
   "p_s": 220,
   "n": 4
  },
  {
   "launch_t": 573.7,
   "lpd": 2.87,
   "water_t": 308.2,
   "t_sortie": 2.28,
   "residence": 12.4,
   "strict": false,
   "waiver": true,
   "kappa": 417.0,
   "p_s": 220,
   "n": 5
  },
  {
   "launch_t": 598.1,
   "lpd": 14.95,
   "water_t": 319.5,
   "t_sortie": 2.26,
   "residence": 3.3,
   "strict": false,
   "waiver": true,
   "kappa": 417.0,
   "p_s": 230,
   "n": 1
  },
  {
   "launch_t": 598.1,
   "lpd": 7.48,
   "water_t": 319.5,
   "t_sortie": 2.26,
   "residence": 5.5,
   "strict": false,
   "waiver": true,
   "kappa": 417.0,
   "p_s": 230,
   "n": 2
  },
  {
   "launch_t": 598.1,
   "lpd": 4.98,
   "water_t": 319.5,
   "t_sortie": 2.26,
   "residence": 7.8,
   "strict": false,
   "waiver": true,
   "kappa": 417.0,
   "p_s": 230,
   "n": 3
  },
  {
   "launch_t": 598.1,
   "lpd": 3.74,
   "water_t": 319.5,
   "t_sortie": 2.26,
   "residence": 10.0,
   "strict": false,
   "waiver": true,
   "kappa": 417.0,
   "p_s": 230,
   "n": 4
  },
  {
   "launch_t": 598.1,
   "lpd": 2.99,
   "water_t": 319.5,
   "t_sortie": 2.26,
   "residence": 12.3,
   "strict": false,
   "waiver": true,
   "kappa": 417.0,
   "p_s": 230,
   "n": 5
  },
  {
   "launch_t": 622.4,
   "lpd": 15.56,
   "water_t": 330.7,
   "t_sortie": 2.24,
   "residence": 3.2,
   "strict": false,
   "waiver": true,
   "kappa": 417.0,
   "p_s": 240,
   "n": 1
  },
  {
   "launch_t": 622.4,
   "lpd": 7.78,
   "water_t": 330.7,
   "t_sortie": 2.24,
   "residence": 5.5,
   "strict": false,
   "waiver": true,
   "kappa": 417.0,
   "p_s": 240,
   "n": 2
  },
  {
   "launch_t": 622.4,
   "lpd": 5.19,
   "water_t": 330.7,
   "t_sortie": 2.24,
   "residence": 7.7,
   "strict": false,
   "waiver": true,
   "kappa": 417.0,
   "p_s": 240,
   "n": 3
  },
  {
   "launch_t": 622.4,
   "lpd": 3.89,
   "water_t": 330.7,
   "t_sortie": 2.24,
   "residence": 10.0,
   "strict": false,
   "waiver": true,
   "kappa": 417.0,
   "p_s": 240,
   "n": 4
  },
  {
   "launch_t": 622.4,
   "lpd": 3.11,
   "water_t": 330.7,
   "t_sortie": 2.24,
   "residence": 12.2,
   "strict": false,
   "waiver": true,
   "kappa": 417.0,
   "p_s": 240,
   "n": 5
  },
  {
   "launch_t": 646.8,
   "lpd": 16.17,
   "water_t": 342.0,
   "t_sortie": 2.22,
   "residence": 3.2,
   "strict": false,
   "waiver": true,
   "kappa": 417.0,
   "p_s": 250,
   "n": 1
  },
  {
   "launch_t": 646.8,
   "lpd": 8.08,
   "water_t": 342.0,
   "t_sortie": 2.22,
   "residence": 5.4,
   "strict": false,
   "waiver": true,
   "kappa": 417.0,
   "p_s": 250,
   "n": 2
  },
  {
   "launch_t": 646.8,
   "lpd": 5.39,
   "water_t": 342.0,
   "t_sortie": 2.22,
   "residence": 7.7,
   "strict": false,
   "waiver": true,
   "kappa": 417.0,
   "p_s": 250,
   "n": 3
  },
  {
   "launch_t": 646.8,
   "lpd": 4.04,
   "water_t": 342.0,
   "t_sortie": 2.22,
   "residence": 9.9,
   "strict": false,
   "waiver": true,
   "kappa": 417.0,
   "p_s": 250,
   "n": 4
  },
  {
   "launch_t": 646.8,
   "lpd": 3.23,
   "water_t": 342.0,
   "t_sortie": 2.22,
   "residence": 12.1,
   "strict": false,
   "waiver": true,
   "kappa": 417.0,
   "p_s": 250,
   "n": 5
  }
 ]
}